aito/__init__.py
aito/api.py
aito/exceptions.py
aito/schema.py
aito/cli/__init__.py
aito/cli/__main__.py
aito/cli/main_parser.py
aito/cli/parser.py
aito/cli/sub_commands/__init__.py
aito/cli/sub_commands/convert_sub_command.py
aito/cli/sub_commands/database_sub_command.py
aito/cli/sub_commands/infer_table_schema_sub_command.py
aito/cli/sub_commands/sub_command.py
aito/client/__init__.py
aito/client/aito_client.py
aito/client/requests/__init__.py
aito/client/requests/aito_request.py
aito/client/requests/data_api_request.py
aito/client/requests/job_api_request.py
aito/client/requests/modify_operations.py
aito/client/requests/query_api_request.py
aito/client/requests/schema_api_request.py
aito/client/responses/__init__.py
aito/client/responses/aito_response.py
aito/client/responses/job_api_response.py
aito/client/responses/query_api_response.py
aito/client/responses/schema_api_response.py
aito/utils/__init__.py
aito/utils/_credentials_file_utils.py
aito/utils/_file_utils.py
aito/utils/_generic_utils.py
aito/utils/_json_format.py
aito/utils/_typing.py
aito/utils/data_frame_handler.py
aito/utils/sql_connection.py
aitoai-0.5.4.dist-info/licenses/LICENSE
aitoai-0.5.4.dist-info/METADATA
aitoai-0.5.4.dist-info/WHEEL
aitoai-0.5.4.dist-info/entry_points.txt
aitoai-0.5.4.dist-info/top_level.txt
aitoai-0.5.4.dist-info/RECORD
