Metadata-Version: 2.4
Name: aitoai
Version: 0.5.4
Summary: Aito.ai Python SDK
Home-page: https://github.com/AitoDotAI/aito-python-tools
Author: aito.ai
Author-email: admin@aito.ai
Project-URL: Documentation, https://aito-python-sdk.readthedocs.io/en/latest/
Project-URL: Source, https://github.com/AitoDotAI/aito-python-tools
Project-URL: Tracker, https://github.com/AitoDotAI/aito-python-tools/issues
Classifier: Development Status :: 3 - Alpha
Classifier: Intended Audience :: Developers
Classifier: Natural Language :: English
Classifier: License :: OSI Approved :: MIT License
Classifier: Operating System :: MacOS :: MacOS X
Classifier: Operating System :: POSIX
Classifier: Operating System :: POSIX :: BSD
Classifier: Operating System :: POSIX :: Linux
Classifier: Operating System :: Microsoft :: Windows
Classifier: Programming Language :: Python
Classifier: Programming Language :: Python :: 3
Classifier: Programming Language :: Python :: 3.9
Classifier: Programming Language :: Python :: 3.10
Classifier: Programming Language :: Python :: 3.11
Classifier: Programming Language :: Python :: 3.12
Requires-Python: >=3.9
License-File: LICENSE
Requires-Dist: pandas~=1.0; python_version < "3.9"
Requires-Dist: pandas~=2.0; python_version >= "3.9"
Requires-Dist: requests<4,>=2.22
Requires-Dist: packaging>=21.0
Requires-Dist: aiohttp<4.0,>=3.6.1
Requires-Dist: ndjson>=0.2.0
Requires-Dist: langdetect<2.0,>=1.0.7
Requires-Dist: argcomplete<4.0,>=1.11.1
Requires-Dist: xlrd<3.0,>=1.1
Requires-Dist: jsonschema~=3.0
Requires-Dist: openpyxl>=3.0.7
Requires-Dist: fastparquet>=0.8
Dynamic: author
Dynamic: author-email
Dynamic: classifier
Dynamic: description
Dynamic: description-content-type
Dynamic: home-page
Dynamic: license-file
Dynamic: project-url
Dynamic: requires-dist
Dynamic: requires-python
Dynamic: summary
